goopylib/__init__.py
goopylib/_internal.py
goopylib/imports.py
goopylib/color/__init__.py
goopylib/color/color.cp311-win_amd64.pyd
goopylib/color/color.pyi
goopylib/color/random.py
goopylib/color/w3cx11.py
goopylib/core/__init__.py
goopylib/core/core.cp311-win_amd64.pyd
goopylib/core/core.pyi
goopylib/core/window.cp311-win_amd64.pyd
goopylib/core/window.pyi
goopylib/events/__init__.py
goopylib/events/keyboard.py
goopylib/events/mouse.py
goopylib/layout/__init__.py
goopylib/layout/_internal.py
goopylib/layout/align_offset_funcs.py
goopylib/layout/div.py
goopylib/layout/flex.py
goopylib/layout/manager.py
goopylib/maths/__init__.py
goopylib/maths/easing.cp311-win_amd64.pyd
goopylib/maths/easing.pyi
goopylib/maths/packing/__init__.py
goopylib/maths/packing/packing.py
goopylib/maths/packing/shelf.py
goopylib/objects/__init__.py
goopylib/objects/circle.cp311-win_amd64.pyd
goopylib/objects/circle.pyi
goopylib/objects/ellipse.cp311-win_amd64.pyd
goopylib/objects/ellipse.pyi
goopylib/objects/image.cp311-win_amd64.pyd
goopylib/objects/image.pyi
goopylib/objects/line.cp311-win_amd64.pyd
goopylib/objects/line.pyi
goopylib/objects/quad.cp311-win_amd64.pyd
goopylib/objects/quad.pyi
goopylib/objects/rectangle.cp311-win_amd64.pyd
goopylib/objects/rectangle.pyi
goopylib/objects/renderable.cp311-win_amd64.pyd
goopylib/objects/renderable.pyi
goopylib/objects/triangle.cp311-win_amd64.pyd
goopylib/objects/triangle.pyi
goopylib/scene/__init__.py
goopylib/scene/camera.cp311-win_amd64.pyd
goopylib/scene/camera.pyi
goopylib/scene/camera_controller.cp311-win_amd64.pyd
goopylib/scene/camera_controller.pyi
goopylib-2.1.0.data/data/goopylib/goopylib.dll
goopylib-2.1.0.dist-info/LICENSE.md
goopylib-2.1.0.dist-info/METADATA
goopylib-2.1.0.dist-info/WHEEL
goopylib-2.1.0.dist-info/top_level.txt
goopylib-2.1.0.dist-info/RECORD
