Metadata-Version: 2.1
Name: goopylib
Version: 2.1.0
Summary: A powerful game, graphics, and application development library for Python
Home-page: https://github.com/BhavyeMathur/goopylib
Author: Bhavye Mathur
Author-email: Bhavye Mathur <bhavyemathur@gmail.com>
License: Mozilla Public License Version 2.0
Project-URL: Homepage, https://github.com/BhavyeMathur/goopylib
Project-URL: Bug Tracker, https://github.com/BhavyeMathur/goopylib/issues
Keywords: Python GUI,Graphics,2D Graphics,OpenGL,Game Development,Game Engine,Application Development,User Interfaces
Classifier: Intended Audience :: Developers
Classifier: Topic :: Games/Entertainment
Classifier: Topic :: Software Development :: Libraries :: Application Frameworks
Classifier: Topic :: Multimedia :: Graphics
Classifier: Topic :: Software Development :: User Interfaces
Classifier: License :: OSI Approved :: Mozilla Public License 2.0 (MPL 2.0)
Classifier: Operating System :: MacOS
Classifier: Operating System :: Microsoft :: Windows
Classifier: Operating System :: Unix
Classifier: Programming Language :: C
Classifier: Programming Language :: C++
Classifier: Programming Language :: Python :: 3.8
Classifier: Programming Language :: Python :: 3.9
Classifier: Programming Language :: Python :: 3.10
Classifier: Programming Language :: Python :: 3.11
Classifier: Programming Language :: Python :: Implementation :: CPython
Classifier: Programming Language :: Python :: Implementation :: PyPy
Requires-Python: >=3.8
License-File: LICENSE.md
